ukbparse/__init__.py
ukbparse/__main__.py
ukbparse/cleaning.py
ukbparse/cleaning_functions.py
ukbparse/config.py
ukbparse/custom.py
ukbparse/datatable.py
ukbparse/dryrun.py
ukbparse/exporting.py
ukbparse/exporting_hdf5.py
ukbparse/exporting_tsv.py
ukbparse/expression.py
ukbparse/fileinfo.py
ukbparse/hierarchy.py
ukbparse/icd10.py
ukbparse/importing.py
ukbparse/loadtables.py
ukbparse/main.py
ukbparse/merging.py
ukbparse/metaproc_functions.py
ukbparse/processing.py
ukbparse/processing_functions.py
ukbparse/processing_functions_core.py
ukbparse/storage.py
ukbparse/util.py
ukbparse/data/categories.tsv
ukbparse/data/datacodings_navalues.tsv
ukbparse/data/datacodings_recoding.tsv
ukbparse/data/encoding.txt
ukbparse/data/field.txt
ukbparse/data/processing.tsv
ukbparse/data/types.tsv
ukbparse/data/variables_clean.tsv
ukbparse/data/variables_navalues.tsv
ukbparse/data/variables_parentvalues.tsv
ukbparse/data/variables_recoding.tsv
ukbparse/data/hierarchy/coding1001.tsv
ukbparse/data/hierarchy/coding1003.tsv
ukbparse/data/hierarchy/coding1005.tsv
ukbparse/data/hierarchy/coding1006.tsv
ukbparse/data/hierarchy/coding19.tsv
ukbparse/data/hierarchy/coding2.tsv
ukbparse/data/hierarchy/coding22000.tsv
ukbparse/data/hierarchy/coding240.tsv
ukbparse/data/hierarchy/coding259.tsv
ukbparse/data/hierarchy/coding264.tsv
ukbparse/data/hierarchy/coding265.tsv
ukbparse/data/hierarchy/coding266.tsv
ukbparse/data/hierarchy/coding267.tsv
ukbparse/data/hierarchy/coding268.tsv
ukbparse/data/hierarchy/coding3.tsv
ukbparse/data/hierarchy/coding38.tsv
ukbparse/data/hierarchy/coding39.tsv
ukbparse/data/hierarchy/coding47.tsv
ukbparse/data/hierarchy/coding49.tsv
ukbparse/data/hierarchy/coding497.tsv
ukbparse/data/hierarchy/coding5.tsv
ukbparse/data/hierarchy/coding50.tsv
ukbparse/data/hierarchy/coding51.tsv
ukbparse/data/hierarchy/coding54.tsv
ukbparse/data/hierarchy/coding56.tsv
ukbparse/data/hierarchy/coding59.tsv
ukbparse/data/hierarchy/coding6.tsv
ukbparse/data/hierarchy/coding60.tsv
ukbparse-0.22.0.dist-info/LICENSE
ukbparse-0.22.0.dist-info/METADATA
ukbparse-0.22.0.dist-info/WHEEL
ukbparse-0.22.0.dist-info/entry_points.txt
ukbparse-0.22.0.dist-info/top_level.txt
ukbparse-0.22.0.dist-info/RECORD
