Metadata-Version: 2.1
Name: ukbparse
Version: 0.22.0
Summary: The FMRIB UK Biobank data processing library
Home-page: https://git.fmrib.ox.ac.uk/fsl/ukbparse
Author: Paul McCarthy
Author-email: pauldmccarthy@gmail.com
License: Apache License Version 2.0
Platform: UNKNOWN
Classifier: Programming Language :: Python :: 3.5
Classifier: Programming Language :: Python :: 3.6
Classifier: Programming Language :: Python :: 3.7
Requires-Dist: h5py
Requires-Dist: numpy
Requires-Dist: pandas
Requires-Dist: pyparsing
Requires-Dist: six
Requires-Dist: tables
Requires-Dist: beautifulsoup4
Requires-Dist: lxml
Provides-Extra: demo
Requires-Dist: jupyter ; extra == 'demo'
Requires-Dist: notebook ; extra == 'demo'
Requires-Dist: bash-kernel ; extra == 'demo'
Requires-Dist: pygments ; extra == 'demo'
Provides-Extra: test
Requires-Dist: jupyter ; extra == 'test'
Requires-Dist: notebook ; extra == 'test'
Requires-Dist: bash-kernel ; extra == 'test'
Requires-Dist: pygments ; extra == 'test'
